markus/__init__.py
markus/filters.py
markus/main.py
markus/pytest_plugin.py
markus/testing.py
markus/utils.py
markus/backends/__init__.py
markus/backends/cloudwatch.py
markus/backends/datadog.py
markus/backends/logging.py
markus/backends/statsd.py
markus-5.2.0.dist-info/licenses/LICENSE
markus-5.2.0.dist-info/METADATA
markus-5.2.0.dist-info/WHEEL
markus-5.2.0.dist-info/entry_points.txt
markus-5.2.0.dist-info/top_level.txt
markus-5.2.0.dist-info/RECORD
