Metadata-Version: 2.4
Name: markus
Version: 5.2.0
Summary: Metrics system for generating statistics about your app
Author: Will Kahn-Greene
License: MPLv2
Project-URL: Homepage, https://github.com/mozilla-services/markus
Project-URL: Documentation, https://markus.readthedocs.io/
Project-URL: Source, https://github.com/mozilla-services/markus/
Project-URL: Issues, https://github.com/mozilla-services/markus/issues
Keywords: metrics,datadog,statsd
Classifier: Development Status :: 5 - Production/Stable
Classifier: Intended Audience :: Developers
Classifier: License :: OSI Approved :: Mozilla Public License 2.0 (MPL 2.0)
Classifier: Natural Language :: English
Classifier: Programming Language :: Python :: 3 :: Only
Classifier: Programming Language :: Python :: 3.10
Classifier: Programming Language :: Python :: 3.11
Classifier: Programming Language :: Python :: 3.12
Classifier: Programming Language :: Python :: 3.13
Classifier: Programming Language :: Python :: 3.14
Requires-Python: >=3.10
License-File: LICENSE
Provides-Extra: datadog
Requires-Dist: datadog>=0.45.0; extra == "datadog"
Provides-Extra: statsd
Requires-Dist: statsd; extra == "statsd"
Provides-Extra: dev
Requires-Dist: build; extra == "dev"
Requires-Dist: pytest; extra == "dev"
Requires-Dist: ruff; extra == "dev"
Requires-Dist: Sphinx; extra == "dev"
Requires-Dist: sphinx_rtd_theme; extra == "dev"
Requires-Dist: time-machine; extra == "dev"
Requires-Dist: tomli>=1.1.0; python_version < "3.11" and extra == "dev"
Requires-Dist: tox; extra == "dev"
Requires-Dist: tox-gh-actions; extra == "dev"
Requires-Dist: tox-uv; extra == "dev"
Requires-Dist: twine; extra == "dev"
Requires-Dist: wheel; extra == "dev"
Dynamic: license-file
